Memory.v
module Memory(A1, A2, A3, WD3, RD1, RD2, WE3, clk);
 parameter D = 1;
 input WE3, clk;
 input [31:0] A1, A2, A3, WD3;
 output reg [31:0] RD1, RD2;

 reg [7:0] mem [D-1:0];
 
 always @* begin
  RD1<={mem[A1], mem[A1+1], mem[A1+2], mem[A1+3]};
  RD2<={mem[A2], mem[A2+1], mem[A2+2], mem[A2+3]};
 end

 always @(posedge clk)
  if(WE3==1) {mem[A3], mem[A3+1]}=WD3;

endmodule

PIPE.v
module PIPE(in, out, clk);
 parameter L=1;
 input [L-1:0] in;
 input clk;
 output reg [L-1:0] out;
 
 always @(negedge clk)
  out=in;

endmodule

ALU.v
module ALU(SrcA, SrcB, ALUControl, Flags, ALUResult);
 
 parameter ADD=3'b000, SUB=3'b001, MUL=3'b010,
           OR=3'b011, XOR=3'b100, SLT=3'b101,
           SRA=3'b110, SRL=3'b111;
 
 input [31:0] SrcA, SrcB;
 input [2:0] ALUControl;
 output reg [31:0] ALUResult;
 output [3:0] Flags;
  
 assign Flags = { SrcA==SrcB, SrcA!=SrcB, SrcA<SrcB, !(SrcA<SrcB) };//EQ, NEQ, BLT, BGE

 always @*
  case(ALUControl)
   ADD: ALUResult=SrcA+SrcB;
   SUB: ALUResult=SrcA-SrcB;
   MUL: ALUResult=SrcA*SrcB;
   XOR: ALUResult=SrcA^SrcB;
   SLT: ALUResult=SrcA<SrcB;
   SRA: ALUResult=SrcA>>>SrcB;
   SRL: ALUResult=SrcA>>SrcB;
   default: ALUResult=32'bx;
  endcase

endmodule

RegisterFile.v
module RegisterFile(A1, A2, A3, WD3, WE3, clk, reset, RD1, RD2);
 input clk, WE3, reset;
 input [4:0] A1, A2, A3;
 input [31:0] WD3;
 output [31:0] RD1, RD2; 
 
 reg [31:0] RD1_t, RD2_t;
  
 reg [31:0] bank [31:0];

 reg [5:0] counter;
 
 assign RD1 = A1!=0 ? RD1_t: 32'b0;
 assign RD2 = A2!=0 ? RD2_t: 32'b0;
 
 always@*
  if(!reset) begin
   RD1_t<=bank[A1];
   RD2_t<=bank[A2];
  end
 
 always @(posedge clk or posedge reset)
  if(reset)
    for(counter=0; counter<32; counter=counter+1)
     bank[counter]=32'd0;
  else
   if(WE3 && A3!=0)
    bank[A3]=WD3;
   else;

endmodule

CORE.v
//Inputs
`define IM_RD in[31:0]
`define DM_RD in[63:32]
//Outputs
`define IM_A out[31:0]
`define DM_A out[63:32]
`define DM_WD out[95:64]
`define DM_WE out[96]

module CORE(in, out, clk, reset);

 input [63:0] in;
 output [96:0] out;
 input clk, reset;

 //IF
 //PC
 reg [31:0] PC;
 wire [31:0] PC4;
 wire [31:0] MUX1;
 wire S1;
 assign PC4 = PC + 32'd4;
 assign MUX1 = S1 ? MUX6 : PC4;
 assign `IM_A = PC;
 always @(posedge clk or posedge reset) 
  if(reset) PC=0;
  else PC = MUX1;
 //IF_DEC
 wire [31:0] PC4_D, IM_RD_D, PC_D;
 PIPE IFDEC(.in({PC, `IM_RD, PC4}), .out({PC_D, IM_RD_D, PC4_D}), .clk(clk));
 defparam IFDEC.L = 96;

 //DEC
 wire S2, S0, S9;
 wire [31:0] RD1, RD2;
 wire [31:0] MUX0;
 wire [31:0] MUX9;
 wire [31:0] Imm;
 assign MUX0 = S0 ? { {25{IM_RD_D[31]}}, IM_RD_D[31:25]  }: { {20{IM_RD_D[31]}}, IM_RD_D[31:20]};
 assign MUX9 = S9 ? { {12{IM_RD_D[31]}}, IM_RD_D[31:12]  } : MUX0;
 assign Imm = MUX9;
 RegisterFile RF(.A1(IM_RD_D[19:15]), .A2(IM_RD_D[24:20]), .A3(Rd_W), .WD3(MUX8), .WE3(S2), .clk(clk), .reset(reset), .RD1(RD1), .RD2(RD2));
 //SignExtend SE(.in(MUX9), .out(Imm));

 //DEC/EX
 wire [31:0] PC_E, Imm_E, RD2_E, RD1_E, PC4_E;
 wire [4:0] Rd_E;
 PIPE DECEX(.in({PC_D, Imm, RD2, RD1, IM_RD_D[11:7], PC4_D}), .out({PC_E, Imm_E, RD2_E, RD1_E, Rd_E, PC4_E}), .clk(clk));
 defparam DECEX.L = 165;
 
 //EX
 wire S3;
 wire [2:0] S4;
 wire [3:0] Flags_E;
 wire [31:0] MUX3, ADDPC_E, ALUResult_E;
 assign MUX3 = S3 ? Imm_E : RD2_E;
 assign ADDPC_E = (Imm_E + PC_E)<<2;
 ALU ALUB(.SrcA(RD1_E), .SrcB(MUX3), .ALUControl(S4), .Flags(Flags_E), .ALUResult(ALUResult_E));

 //EX/MEM
 wire [31:0] ADDPC_M, RD2_M, ALUResult_M, PC4_M;
 wire [3:0] Flags_M;
 wire [4:0] Rd_M;
 PIPE EXMEM(.in({ADDPC_E, RD2_E, ALUResult_E, Flags_E, Rd_E, PC4_E}), .out({ADDPC_M, RD2_M, ALUResult_M, Flags_M, Rd_M, PC4_M}), .clk(clk));
 defparam EXMEM.L = 137;

 //MEM
 wire S5, S6;
 wire [31:0] MUX6;
 assign MUX6 = S6 ? ADDPC_M : ALUResult_M;
 assign `DM_A = ALUResult_M;
 assign `DM_WD = RD2_M;
 assign `DM_WE = S5;
 
 //MEM/WB
 wire [31:0] DM_RD_W, ALUResult_W, PC4_W;
 wire [4:0] Rd_W;
 PIPE MEMWB(.in({`DM_RD, ALUResult_M, Rd_M, PC4_M}), .out({DM_RD_W, ALUResult_W, Rd_W, PC4_W}), .clk(clk));
 defparam MEMWB.L = 101;

 //WB
 wire S7, S8;
 wire [31:0] MUX7, MUX8;
 assign MUX7 = S7 ? DM_RD_W: ALUResult_W;
 assign MUX8 = S8 ? MUX7 : PC4_W;

endmodule

CORE_tb.v
module CORE_tb;
 parameter C = 4*2;//5*2
 reg clk, reset;
 wire [63:0] in;
 wire [96:0] out;

 CORE DUT(.in(in), .out(out), .clk(clk), .reset(reset));
 Memory MEM(.A1(out[31:0]), .A2(out[63:32]), .A3(out[63:32]), .WD3(out[95:64]), .RD1(in[31:0]), .RD2(in[63:32]), .WE3(out[96]), .clk(clk));
 defparam MEM.D = 8;
 //Load memory
 initial $readmemb("mem_JAL.txt", MEM.mem);
 //Load registers
 initial begin
  #2;
  DUT.RF.bank[1]=32'habcd;
  DUT.RF.bank[2]=32'd2;
  MEM.mem[4]=8'b0;
  MEM.mem[5]=8'b0;
  MEM.mem[6]=8'b0;
  MEM.mem[7]=8'b0;
  //DUT.RF.bank[2]=32'd4;
 end
 //Assign signals
 assign DUT.S0 = 0;
 assign DUT.S1 = 1;
 assign DUT.S2 = 1;
 assign DUT.S3 = 1'bx;
 assign DUT.S4 = 3'b000;
 assign DUT.S5 = 0;
 assign DUT.S6 = 1'b1;
 assign DUT.S7 = 1'bx;
 assign DUT.S8 = 1'b0;
 assign DUT.S9 = 1'b1;
 
 always #1 clk=!clk;
 //always #1 $display("***IM_RD=%b", DUT.IM_RD_D);
 initial begin
  $dumpfile("core.vcd");
  $dumpvars(0,CORE_tb);
  //$monitor("A2=%h, WD3=%h", out[63:32], out[95:64]);
  $monitor("PC=%b", DUT.PC);
  //$monitor("MUX9=%b", DUT.MUX9);
  print_register();
  print_mem();
  clk=0;
  reset=1;#2;
  reset=0;
  //#C;
  #12;
  print_register();
  print_mem();
  $finish;
  end

  task print_register;
   integer i;
   begin
    $display("Registers:");
    for(i=0; i<32; i=i+1) $display("%s%d=%d","R", i, DUT.RF.bank[i]);
   end
  endtask
  
  task print_mem;
   integer i;
   begin
    $display("MEM:");
    for(i=0; i<C; i=i+1) $display("%s%d=%h","M", i, MEM.mem[i]);
   end
  endtask

endmodule

core.vcd
$date
	Wed Dec 12 21:21:09 2018
$end
$version
	Icarus Verilog
$end
$timescale
	1s
$end
$scope module CORE_tb $end
$var wire 64 ! in [63:0] $end
$var wire 97 " out [96:0] $end
$var reg 1 # clk $end
$var reg 1 $ reset $end
$scope module DUT $end
$var wire 32 % ADDPC_E [31:0] $end
$var wire 32 & ADDPC_M [31:0] $end
$var wire 32 ' ALUResult_E [31:0] $end
$var wire 32 ( ALUResult_M [31:0] $end
$var wire 32 ) ALUResult_W [31:0] $end
$var wire 32 * DM_RD_W [31:0] $end
$var wire 4 + Flags_E [3:0] $end
$var wire 4 , Flags_M [3:0] $end
$var wire 32 - IM_RD_D [31:0] $end
$var wire 32 . Imm [31:0] $end
$var wire 32 / Imm_E [31:0] $end
$var wire 32 0 MUX0 [31:0] $end
$var wire 32 1 MUX1 [31:0] $end
$var wire 32 2 MUX3 [31:0] $end
$var wire 32 3 MUX6 [31:0] $end
$var wire 32 4 MUX7 [31:0] $end
$var wire 32 5 MUX8 [31:0] $end
$var wire 32 6 MUX9 [31:0] $end
$var wire 32 7 PC4 [31:0] $end
$var wire 32 8 PC4_D [31:0] $end
$var wire 32 9 PC4_E [31:0] $end
$var wire 32 : PC4_M [31:0] $end
$var wire 32 ; PC4_W [31:0] $end
$var wire 32 < PC_D [31:0] $end
$var wire 32 = PC_E [31:0] $end
$var wire 32 > RD1 [31:0] $end
$var wire 32 ? RD1_E [31:0] $end
$var wire 32 @ RD2 [31:0] $end
$var wire 32 A RD2_E [31:0] $end
$var wire 32 B RD2_M [31:0] $end
$var wire 5 C Rd_E [4:0] $end
$var wire 5 D Rd_M [4:0] $end
$var wire 5 E Rd_W [4:0] $end
$var wire 1 F S0 $end
$var wire 1 G S1 $end
$var wire 1 H S2 $end
$var wire 1 I S3 $end
$var wire 3 J S4 [2:0] $end
$var wire 1 K S5 $end
$var wire 1 L S6 $end
$var wire 1 M S7 $end
$var wire 1 N S8 $end
$var wire 1 O S9 $end
$var wire 1 P clk $end
$var wire 64 Q in [63:0] $end
$var wire 97 R out [96:0] $end
$var wire 1 S reset $end
$var reg 32 T PC [31:0] $end
$scope module IFDEC $end
$var wire 1 P clk $end
$var wire 96 U in [95:0] $end
$var reg 96 V out [95:0] $end
$upscope $end
$scope module RF $end
$var wire 5 W A1 [4:0] $end
$var wire 5 X A2 [4:0] $end
$var wire 5 Y A3 [4:0] $end
$var wire 32 Z RD1 [31:0] $end
$var wire 32 [ RD2 [31:0] $end
$var wire 32 \ WD3 [31:0] $end
$var wire 1 H WE3 $end
$var wire 1 P clk $end
$var wire 1 S reset $end
$var reg 32 ] RD1_t [31:0] $end
$var reg 32 ^ RD2_t [31:0] $end
$var reg 6 _ counter [5:0] $end
$upscope $end
$scope module DECEX $end
$var wire 1 P clk $end
$var wire 165 ` in [164:0] $end
$var reg 165 a out [164:0] $end
$upscope $end
$scope module ALUB $end
$var wire 3 b ALUControl [2:0] $end
$var wire 4 c Flags [3:0] $end
$var wire 32 d SrcA [31:0] $end
$var wire 32 e SrcB [31:0] $end
$var reg 32 f ALUResult [31:0] $end
$upscope $end
$scope module EXMEM $end
$var wire 1 P clk $end
$var wire 137 g in [136:0] $end
$var reg 137 h out [136:0] $end
$upscope $end
$scope module MEMWB $end
$var wire 1 P clk $end
$var wire 101 i in [100:0] $end
$var reg 101 j out [100:0] $end
$upscope $end
$upscope $end
$scope module MEM $end
$var wire 32 k A1 [31:0] $end
$var wire 32 l A2 [31:0] $end
$var wire 32 m A3 [31:0] $end
$var wire 32 n WD3 [31:0] $end
$var wire 1 o WE3 $end
$var wire 1 P clk $end
$var reg 32 p RD1 [31:0] $end
$var reg 32 q RD2 [31:0] $end
$upscope $end
$scope task print_mem $end
$var integer 32 r i [31:0] $end
$upscope $end
$scope task print_register $end
$var integer 32 s i [31:0] $end
$upscope $end
$upscope $end
$enddefinitions $end
#0
$dumpvars
b100000 s
b1000 r
bx q
b11000000000000000111000010000000 p
0o
bx n
bx m
bx l
b0 k
bx j
bx i
bx00xxxxxxxxxxxxxxxxxxxxxxxxxxxxxxxxxxxxxxxxxxxxxxxxxxxxxxxxxxxxxxxxxxxxxxxxxxxxxxxxxxxxxxxxxxxxxxxxxxxxxxxxx h
bx00xxxxxxxxxxxxxxxxxxxxxxxxxxxxxxxxxxxxxxxxxxxxxxxxxxxxxxxxxxxxxxxxxxxxxxxxxxxxxxxxxxxxxxxxxxxxxxxxxxxxxxxxx g
bx f
bx e
bx d
bx c
b0 b
bx a
bx `
b100000 _
bx ^
bx ]
bx \
bx [
bx Z
bx Y
bx X
bx W
bx V
b1100000000000000011100001000000000000000000000000000000000000100 U
b0 T
1S
b0xxxxxxxxxxxxxxxxxxxxxxxxxxxxxxxxxxxxxxxxxxxxxxxxxxxxxxxxxxxxxxxx00000000000000000000000000000000 R
bx11000000000000000111000010000000 Q
0P
1O
0N
xM
1L
0K
b0 J
xI
1H
1G
0F
bx E
bx D
bx C
bx B
bx A
bx @
bx ?
bx >
bx =
bx <
bx ;
bx :
bx 9
bx 8
b100 7
bx 6
bx 5
bx 4
bx00 3
bx 2
bx00 1
bx 0
bx /
bx .
bx -
bx ,
bx +
bx *
bx )
bx (
bx '
bx00 &
bx00 %
1$
0#
b0xxxxxxxxxxxxxxxxxxxxxxxxxxxxxxxxxxxxxxxxxxxxxxxxxxxxxxxxxxxxxxxx00000000000000000000000000000000 "
bx11000000000000000111000010000000 !
$end
#1
b100000 _
1#
1P
#2
b0 ^
b0 ]
b0 >
b0 Z
b0 @
b0 [
b11111111111111111111110000000000 0
b11111111111111000000000000000111 6
b11111111111111000000000000000111 .
b0 W
b0 X
b100 8
b11000000000000000111000010000000 -
b1111111111111100000000000000011100000000000000000000000000000000000000000000000000000000000000000000100000000000000000000000000000100 `
b0 <
b1100000000000000011100001000000000000000000000000000000000000100 V
0#
0P
0$
0S
#3
bx p
bx !
bx Q
bx00 k
bx00 T
bx 7
bx00xxxxxxxxxxxxxxxxxxxxxxxxxxxxxxxxxxxxxxxxxxxxxxxxxxxxxxxxxxxxxxxx U
b0xxxxxxxxxxxxxxxxxxxxxxxxxxxxxxxxxxxxxxxxxxxxxxxxxxxxxxxxxxxxxxxxxxxxxxxxxxxxxxxxxxxxxxxxxxxxxx00 "
b0xxxxxxxxxxxxxxxxxxxxxxxxxxxxxxxxxxxxxxxxxxxxxxxxxxxxxxxxxxxxxxxxxxxxxxxxxxxxxxxxxxxxxxxxxxxxxx00 R
1#
1P
#4
bx @
bx [
bx >
bx Z
bx ^
bx ]
bx 0
bx 6
bx .
bx W
bx X
bx000000000000000xxx 2
bx000000000000000xxx e
b11111111111100000000000000011100 %
bx 8
bx -
bx00xxxxxxxxxxxxxxxxxxxxxxxxxxxxxxxxxxxxxxxxxxxxxxxxxxxxxxxxxxxxxxxxxxxxxxxxxxxxxxxxxxxxxxxxxxxxxxxxxxxxxxxxxxxxxxxxxxxxxxxxxxxxxxxxxxxxx `
bx00 <
b100 9
b1 C
b0 ?
b0 d
b1111111111110000000000000001110000000000000000000000000000000000xxxxxxxxxxxxxxxxxxxxxxxxxxxxxxxxxxxx0000100000000000000000000000000000100 g
b0 A
b11111111111111000000000000000111 /
b0 =
bx00xxxxxxxxxxxxxxxxxxxxxxxxxxxxxxxxxxxxxxxxxxxxxxxxxxxxxxxxxxxxxxxx V
b1111111111111100000000000000011100000000000000000000000000000000000000000000000000000000000000000000100000000000000000000000000000100 a
0#
0P
#5
1#
1P
#6
b0 n
bx 2
bx e
bx00 %
b100 :
bx0000100000000000000000000000000000100 i
b1 D
b0 B
b0xxxxxxxxxxxxxxxxxxxxxxxxxxxxxxxxxxxxxxxxxxxxxxxxxxxxxxxxxxxxxx00 "
b0xxxxxxxxxxxxxxxxxxxxxxxxxxxxxxxxxxxxxxxxxxxxxxxxxxxxxxxxxxxxxx00 R
b11111111111100000000000000011100 &
b11111111111100000000000000011100 3
b11111111111100000000000000011100 1
bx 9
bx C
bx ?
bx d
bx00xxxxxxxxxxxxxxxxxxxxxxxxxxxxxxxxxxxxxxxxxxxxxxxxxxxxxxxxxxxxxxxxxxxxxxxxxxxxxxxxxxxxxxxxxxxxxxxxxxxxxxxxx g
bx A
bx /
bx00 =
b1111111111110000000000000001110000000000000000000000000000000000xxxxxxxxxxxxxxxxxxxxxxxxxxxxxxxxxxxx0000100000000000000000000000000000100 h
bx00xxxxxxxxxxxxxxxxxxxxxxxxxxxxxxxxxxxxxxxxxxxxxxxxxxxxxxxxxxxxxxxxxxxxxxxxxxxxxxxxxxxxxxxxxxxxxxxxxxxxxxxxxxxxxxxxxxxxxxxxxxxxxxxxxxxxx a
0#
0P
#7
b11111111111100000000000000011100 k
b11111111111100000000000000011100 T
b11111111111100000000000000100000 7
b11111111111100000000000000011100xxxxxxxxxxxxxxxxxxxxxxxxxxxxxxxx11111111111100000000000000100000 U
b0xxxxxxxxxxxxxxxxxxxxxxxxxxxxxxxx11111111111100000000000000011100 "
b0xxxxxxxxxxxxxxxxxxxxxxxxxxxxxxxx11111111111100000000000000011100 R
1#
1P
#8
bx n
b11111111111100000000000000100000 8
b11111111111100000000000000011100xxxxxxxxxxxxxxxxxxxxxxxxxxxxxxxxxxxxxxxxxxxxxxxxxxxxxxxxxxxxxxxxxxxxxxxxxxxxxxxxxxxxxxxxxxxxxxxxxxxxx11111111111100000000000000100000 `
b11111111111100000000000000011100 <
bx :
bx i
bx D
bx B
b0xxxxxxxxxxxxxxxxxxxxxxxxxxxxxxxxxxxxxxxxxxxxxxxxxxxxxxxxxxxxxxxx11111111111100000000000000011100 "
b0xxxxxxxxxxxxxxxxxxxxxxxxxxxxxxxxxxxxxxxxxxxxxxxxxxxxxxxxxxxxxxxx11111111111100000000000000011100 R
bx00 &
bx00 3
bx00 1
b100 ;
b100 5
b100 \
b1 E
b1 Y
b11111111111100000000000000011100xxxxxxxxxxxxxxxxxxxxxxxxxxxxxxxx11111111111100000000000000100000 V
bx00xxxxxxxxxxxxxxxxxxxxxxxxxxxxxxxxxxxxxxxxxxxxxxxxxxxxxxxxxxxxxxxxxxxxxxxxxxxxxxxxxxxxxxxxxxxxxxxxxxxxxxxxx h
bx0000100000000000000000000000000000100 j
0#
0P
#9
bx00 k
bx00 T
bx 7
bx00xxxxxxxxxxxxxxxxxxxxxxxxxxxxxxxxxxxxxxxxxxxxxxxxxxxxxxxxxxxxxxxx U
b0xxxxxxxxxxxxxxxxxxxxxxxxxxxxxxxxxxxxxxxxxxxxxxxxxxxxxxxxxxxxxxxxxxxxxxxxxxxxxxxxxxxxxxxxxxxxxx00 "
b0xxxxxxxxxxxxxxxxxxxxxxxxxxxxxxxxxxxxxxxxxxxxxxxxxxxxxxxxxxxxxxxxxxxxxxxxxxxxxxxxxxxxxxxxxxxxxx00 R
1#
1P
#10
bx ;
bx 5
bx \
bx E
bx Y
bx00xxxxxxxxxxxxxxxxxxxxxxxxxxxxxxxxxxxxxxxxxxxxxxxxxxxxxxxxxxxxxxxxxxxxxxxxx11111111111100000000000000100000 g
b11111111111100000000000000100000 9
b11111111111100000000000000011100 =
bx 8
bx00xxxxxxxxxxxxxxxxxxxxxxxxxxxxxxxxxxxxxxxxxxxxxxxxxxxxxxxxxxxxxxxxxxxxxxxxxxxxxxxxxxxxxxxxxxxxxxxxxxxxxxxxxxxxxxxxxxxxxxxxxxxxxxxxxxxxx `
bx00 <
bx j
b11111111111100000000000000011100xxxxxxxxxxxxxxxxxxxxxxxxxxxxxxxxxxxxxxxxxxxxxxxxxxxxxxxxxxxxxxxxxxxxxxxxxxxxxxxxxxxxxxxxxxxxxxxxxxxxx11111111111100000000000000100000 a
bx00xxxxxxxxxxxxxxxxxxxxxxxxxxxxxxxxxxxxxxxxxxxxxxxxxxxxxxxxxxxxxxxx V
0#
0P
#11
1#
1P
#12
bx00xxxxxxxxxxxxxxxxxxxxxxxxxxxxxxxxxxxxxxxxxxxxxxxxxxxxxxxxxxxxxxxxxxxxxxxxxxxxxxxxxxxxxxxxxxxxxxxxxxxxxxxxx g
bx 9
bx00 =
bx11111111111100000000000000100000 i
b11111111111100000000000000100000 :
bx00xxxxxxxxxxxxxxxxxxxxxxxxxxxxxxxxxxxxxxxxxxxxxxxxxxxxxxxxxxxxxxxxxxxxxxxxxxxxxxxxxxxxxxxxxxxxxxxxxxxxxxxxxxxxxxxxxxxxxxxxxxxxxxxxxxxxx a
bx00xxxxxxxxxxxxxxxxxxxxxxxxxxxxxxxxxxxxxxxxxxxxxxxxxxxxxxxxxxxxxxxxxxxxxxxxx11111111111100000000000000100000 h
0#
0P
#13
1#
1P
#14
b11111111111100000000000000100000 ;
b11111111111100000000000000100000 5
b11111111111100000000000000100000 \
bx i
bx :
bx11111111111100000000000000100000 j
bx00xxxxxxxxxxxxxxxxxxxxxxxxxxxxxxxxxxxxxxxxxxxxxxxxxxxxxxxxxxxxxxxxxxxxxxxxxxxxxxxxxxxxxxxxxxxxxxxxxxxxxxxxx h
0#
0P
b1000 r
b100000 s
